annchor/__init__.py
annchor/annchor.py
annchor/datasets.py
annchor/distances.py
annchor/error_predictors.py
annchor/pickers.py
annchor/query_functions.py
annchor/regressors.py
annchor/samplers.py
annchor/utils.py
annchor/data/digits_data.npz
annchor/data/digits_data_large.npz
annchor/data/edit_data.npz
annchor/data/graph.npz
annchor/data/graph_sp.gz
annchor/data/graph_sp_data.npz
annchor/data/strings_data.npz
annchor/data/wasserstein_matrix.npz
annchor-1.1.1.dist-info/licenses/LICENSE
annchor-1.1.1.dist-info/METADATA
annchor-1.1.1.dist-info/WHEEL
annchor-1.1.1.dist-info/top_level.txt
annchor-1.1.1.dist-info/RECORD
