Metadata-Version: 2.4
Name: annchor
Version: 1.1.1
Summary: Fast k-NN graph construction for slow metrics
Author-email: Jonathan H <oss@gchq.gov.uk>
License: BSD License
Project-URL: Homepage, https://github.com/gchq/annchor
Project-URL: Documentation, https://annchor.readthedocs.io
Project-URL: Repository, https://github.com/gchq/annchor
Project-URL: Bug Tracker, https://github.com/gchq/annchor/issues
Keywords: nearest-neighbors
Classifier: Development Status :: 4 - Beta
Classifier: License :: OSI Approved :: BSD License
Classifier: Programming Language :: Python :: 3
Classifier: Programming Language :: Python :: 3.9
Classifier: Programming Language :: Python :: 3.10
Classifier: Programming Language :: Python :: 3.11
Classifier: Programming Language :: Python :: 3.12
Classifier: Programming Language :: Python :: 3.13
Requires-Python: >=3.9
License-File: LICENSE
Requires-Dist: joblib>=1.0.1
Requires-Dist: numba>=0.55.1
Requires-Dist: numpy<2,>=1.18
Requires-Dist: pynndescent>=0.5.4
Requires-Dist: python-Levenshtein>=0.12.2
Requires-Dist: scikit-learn>=0.0
Requires-Dist: scipy>=1.7.0
Requires-Dist: tqdm>=4.61.2
Provides-Extra: test
Requires-Dist: networkx; extra == "test"
Requires-Dist: pytest; extra == "test"
Dynamic: license-file
